snakemake_executor_plugin_lsf/__init__.py
snakemake_executor_plugin_lsf-0.2.6.dist-info/LICENSE
snakemake_executor_plugin_lsf-0.2.6.dist-info/METADATA
snakemake_executor_plugin_lsf-0.2.6.dist-info/WHEEL
snakemake_executor_plugin_lsf-0.2.6.dist-info/RECORD
